airsimdroneracinglab/__init__.py
airsimdroneracinglab/baseline.py
airsimdroneracinglab/client.py
airsimdroneracinglab/pfm.py
airsimdroneracinglab/types.py
airsimdroneracinglab/utils.py
airsimdroneracinglab-1.0.2.dist-info/LICENSE
airsimdroneracinglab-1.0.2.dist-info/METADATA
airsimdroneracinglab-1.0.2.dist-info/WHEEL
airsimdroneracinglab-1.0.2.dist-info/top_level.txt
airsimdroneracinglab-1.0.2.dist-info/RECORD
