Metadata-Version: 2.1
Name: airsimdroneracinglab
Version: 1.0.2
Summary: Python package for AirSim Drone Racing Lab, built on Microsoft AirSim - an open source simulator based on Unreal Engine for autonomous vehicles from Microsoft AI & Research
Home-page: https://github.com/microsoft/AirSim-Drone-Racing-Lab
Author: Microsoft, Ratnesh Madaan, Nicholas Gyde, Sai Vemprala
Author-email: ratnesh.madaan@microsoft.com, v-nigyde@microsoft.com, sai.vemprala@microsoft.com
License: MIT
Platform: UNKNOWN
Classifier: Programming Language :: Python :: 3
Classifier: License :: OSI Approved :: MIT License
Classifier: Operating System :: OS Independent
Requires-Dist: msgpack-rpc-python
Requires-Dist: numpy
